instascraper/__init__.py
instascraper/instagram.py
instascraper/main.py
instascraper/setup_env.py
instascraper_pro-0.4.dist-info/METADATA
instascraper_pro-0.4.dist-info/WHEEL
instascraper_pro-0.4.dist-info/entry_points.txt
instascraper_pro-0.4.dist-info/top_level.txt
instascraper_pro-0.4.dist-info/RECORD
