Metadata-Version: 2.1
Name: instascraper-pro
Version: 0.4
Requires-Dist: selenium
Requires-Dist: webdriver-manager
Requires-Dist: easyocr
Requires-Dist: opencv-python
Requires-Dist: pandas
